ppgee/__init__.py
ppgee/__main__.py
ppgee/client.py
ppgee/errors.py
ppgee/http.py
ppgee/pages/__init__.py
ppgee/pages/attendency.py
ppgee/parsers/__init__.py
ppgee/parsers/attendency.py
ppgee/permissions.py
ppgee-0.2.1.dist-info/LICENSE
ppgee-0.2.1.dist-info/METADATA
ppgee-0.2.1.dist-info/WHEEL
ppgee-0.2.1.dist-info/entry_points.txt
ppgee-0.2.1.dist-info/RECORD
